FortniteGGAPI/__init__.py
fortniteggapi-1.0.1.dist-info/METADATA
fortniteggapi-1.0.1.dist-info/WHEEL
fortniteggapi-1.0.1.dist-info/top_level.txt
fortniteggapi-1.0.1.dist-info/RECORD
