Metadata-Version: 2.4
Name: FortniteGGAPI
Version: 1.0.1
Summary: An Async Python API Wrapper for Fortnite.GG
Author: Pirxcy
Requires-Python: >=3.12
Dynamic: author
